<annotation>
	<folder>drink</folder>
	<filename>drink.567dc552-eb90-4eaf-9661-0cf818d73263.jpg</filename>
	<path>C:\Users\shawn\OneDrive\Desktop\dataset\dataset\drink\drink.567dc552-eb90-4eaf-9661-0cf818d73263.jpg</path>
	<source>
		<database>Unknown</database>
	</source>
	<size>
		<width>640</width>
		<height>480</height>
		<depth>3</depth>
	</size>
	<segmented>0</segmented>
	<object>
		<name>drink</name>
		<pose>Unspecified</pose>
		<truncated>0</truncated>
		<difficult>0</difficult>
		<bndbox>
			<xmin>264</xmin>
			<ymin>106</ymin>
			<xmax>394</xmax>
			<ymax>282</ymax>
		</bndbox>
	</object>
</annotation>
