<annotation>
	<folder>relaxing</folder>
	<filename>relaxing.47878706-5808-4fec-b581-0cef1477190b.jpg</filename>
	<path>C:\Users\shawn\OneDrive\Desktop\dataset\dataset\relaxing\relaxing.47878706-5808-4fec-b581-0cef1477190b.jpg</path>
	<source>
		<database>Unknown</database>
	</source>
	<size>
		<width>640</width>
		<height>480</height>
		<depth>3</depth>
	</size>
	<segmented>0</segmented>
	<object>
		<name>relaxing</name>
		<pose>Unspecified</pose>
		<truncated>0</truncated>
		<difficult>0</difficult>
		<bndbox>
			<xmin>249</xmin>
			<ymin>333</ymin>
			<xmax>497</xmax>
			<ymax>447</ymax>
		</bndbox>
	</object>
</annotation>
